ucaller_package/__init__.py
ucaller_package/ucaller.py
ucaller-0.0.2.dist-info/LICENSE
ucaller-0.0.2.dist-info/METADATA
ucaller-0.0.2.dist-info/WHEEL
ucaller-0.0.2.dist-info/top_level.txt
ucaller-0.0.2.dist-info/RECORD
