Metadata-Version: 2.1
Name: ucaller
Version: 0.0.2
Summary: Library for using service https://ucaller.ru/doc
Home-page: https://github.com/klishinoleg/ucaller
Author: Klishin Oleg
Author-email: klishinoleg@gmail.com
License: UNKNOWN
Project-URL: Bug Tracker, https://github.com/klishinoleg/ucaller/issues
Platform: UNKNOWN
Classifier: Programming Language :: Python :: 3.7
Classifier: License :: OSI Approved :: MIT License
Classifier: Operating System :: OS Independent
Requires-Python: >=3.7
License-File: LICENSE
